<?xml version="1.0" encoding="utf-8" ?>
<Patch>
  <Operation Class="PatchOperationFindMod">
    <mods>
      <li>[RWY]Dragon's Descent: Void Dwellers</li>
    </mods>
    
          <match Class="PatchOperationSequence">
            <operations>
              <!-- Dragons -->
              <li Class="PatchOperationAdd">
                <xpath>/Defs/AbilityDef[defName="Crows_DragonBondAbility"]/modExtensions/li/allowedAnimals</xpath>
                <value>
                  <li MayRequire="ravvy.DD.Void.Addon">Purple_Nebula_Dragon</li>
                </value>
              </li>

              <li Class="PatchOperationAdd">
                <xpath>/Defs/AbilityDef[defName="Crows_DragonBondAbility"]/modExtensions/li/allowedAnimals</xpath>
                <value>
                  <li MayRequire="ravvy.DD.Void.Addon">Blue_Nebula_Dragon</li>
                </value>
              </li>

              <li Class="PatchOperationAdd">
                <xpath>/Defs/AbilityDef[defName="Crows_DragonBondAbility"]/modExtensions/li/allowedAnimals</xpath>
                <value>
                  <li MayRequire="ravvy.DD.Void.Addon">Red_Nebula_Dragon</li>
                </value>
              </li>

              <li Class="PatchOperationAdd">
                <xpath>/Defs/AbilityDef[defName="Crows_DragonBondAbility"]/modExtensions/li/allowedAnimals</xpath>
                <value>
                  <li MayRequire="ravvy.DD.Void.Addon">EH_Void_Dragon</li>
                </value>
              </li>

              <li Class="PatchOperationAdd">
                <xpath>/Defs/AbilityDef[defName="Crows_DragonBondAbility"]/modExtensions/li/allowedAnimals</xpath>
                <value>
                  <li MayRequire="ravvy.DD.Void.Addon">Destroyer_Void_Dragon</li>
                </value>
              </li>

              <li Class="PatchOperationAdd">
                <xpath>/Defs/AbilityDef[defName="Crows_DragonBondAbility"]/modExtensions/li/allowedAnimals</xpath>
                <value>
                  <li MayRequire="ravvy.DD.Void.Addon">Eater_Void_Dragon</li>
                </value>
              </li>

              <li Class="PatchOperationAdd">
                <xpath>/Defs/AbilityDef[defName="Crows_DragonBondAbility"]/modExtensions/li/allowedAnimals</xpath>
                <value>
                  <li MayRequire="ravvy.DD.Void.Addon">Harbinger_Void_Dragon</li>
                </value>
              </li>

              <li Class="PatchOperationAdd">
                <xpath>/Defs/AbilityDef[defName="Crows_DragonBondAbility"]/modExtensions/li/allowedAnimals</xpath>
                <value>
                  <li MayRequire="ravvy.DD.Void.Addon">Rurelion_Zol_Dragon</li>
                </value>
              </li>
              
              <!-- Eggs -->
              <li Class="PatchOperationAdd">
                <xpath>/Defs/AbilityDef[defName="Crows_DragonBondAbility"]/modExtensions/li/allowedEggs</xpath>
                <value>
                  <li MayRequire="ravvy.DD.Void.Addon">EggRedNebulaDragonFertilized</li>
                </value>
              </li>

                          <li Class="PatchOperationAdd">
                <xpath>/Defs/AbilityDef[defName="Crows_DragonBondAbility"]/modExtensions/li/allowedEggs</xpath>
                <value>
                  <li MayRequire="ravvy.DD.Void.Addon">EggPurpleNebulaDragonFertilized</li>
                </value>
              </li>

              <li Class="PatchOperationAdd">
                <xpath>/Defs/AbilityDef[defName="Crows_DragonBondAbility"]/modExtensions/li/allowedEggs</xpath>
                <value>
                  <li MayRequire="ravvy.DD.Void.Addon">EggBlueNebulaDragonFertilized</li>
                </value>
              </li>

              <li Class="PatchOperationAdd">
                <xpath>/Defs/AbilityDef[defName="Crows_DragonBondAbility"]/modExtensions/li/allowedEggs</xpath>
                <value>
                  <li MayRequire="ravvy.DD.Void.Addon">EggEHVoidDragonFertilized</li>
                </value>
              </li>

              <li Class="PatchOperationAdd">
                <xpath>/Defs/AbilityDef[defName="Crows_DragonBondAbility"]/modExtensions/li/allowedEggs</xpath>
                <value>
                  <li MayRequire="ravvy.DD.Void.Addon">EggDestroyerVoidDragonFertilized</li>
                </value>
              </li>

              <li Class="PatchOperationAdd">
                <xpath>/Defs/AbilityDef[defName="Crows_DragonBondAbility"]/modExtensions/li/allowedEggs</xpath>
                <value>
                  <li MayRequire="ravvy.DD.Void.Addon">EggEaterVoidDragonFertilized</li>
                </value>
              </li>

              <li Class="PatchOperationAdd">
                <xpath>/Defs/AbilityDef[defName="Crows_DragonBondAbility"]/modExtensions/li/allowedEggs</xpath>
                <value>
                  <li MayRequire="ravvy.DD.Void.Addon">EggHarbingerVoidDragonFertilized</li>
                </value>
              </li>

              <li Class="PatchOperationAdd">
                <xpath>/Defs/AbilityDef[defName="Crows_DragonBondAbility"]/modExtensions/li/allowedEggs</xpath>
                <value>
                  <li MayRequire="ravvy.DD.Void.Addon">RurelionDragonFertilized</li>
                </value>
              </li>
            </operations>
          </match>

  </Operation>
</Patch>